cfnbot/__init__.py
cfnbot/cfnbot.py
cfnbot/cli.py
cfnbot-1.0.0.dist-info/DESCRIPTION.rst
cfnbot-1.0.0.dist-info/METADATA
cfnbot-1.0.0.dist-info/RECORD
cfnbot-1.0.0.dist-info/WHEEL
cfnbot-1.0.0.dist-info/entry_points.txt
cfnbot-1.0.0.dist-info/metadata.json
cfnbot-1.0.0.dist-info/top_level.txt
