Metadata-Version: 2.0
Name: cfnbot
Version: 1.0.0
Summary: Makes handling multi-stack deployments to CloudFormation a bit easier
Home-page: https://github.com/inhumantsar/cfnbot
Author: Shaun Martin
Author-email: shaun@samsite.ca
License: Copyright 2016 Shaun Martin
Requires-Dist: PyYAML
Requires-Dist: beeprint
Requires-Dist: boto3
Requires-Dist: click
